bloomtracker/__init__.py
bloomtracker/__main__.py
bloomtracker/async_client.py
bloomtracker/cli.py
bloomtracker/client.py
bloomtracker/constants.py
bloomtracker/exceptions.py
bloomtracker/utils.py
bloomtracker/visualization.py
bloomtracker-0.4.1.data/scripts/bloomtracker
bloomtracker-0.4.1.dist-info/licenses/LICENSE
bloomtracker-0.4.1.dist-info/METADATA
bloomtracker-0.4.1.dist-info/WHEEL
bloomtracker-0.4.1.dist-info/entry_points.txt
bloomtracker-0.4.1.dist-info/top_level.txt
bloomtracker-0.4.1.dist-info/RECORD
