Metadata-Version: 2.4
Name: bloomtracker
Version: 0.4.1
Summary: API client for the 'Deutscher Wetterdienst' to get the current pollen load in Germany
Home-page: https://github.com/striller/BloomTracker
Author: Sascha Triller
Author-email: Sascha Triller <sascha.triller@posteo.de>
License: GNU General Public License v3 or later (GPLv3+)
Project-URL: Homepage, https://github.com/striller/BloomTracker
Project-URL: Issues, https://github.com/striller/BloomTracker/issues
Project-URL: Documentation, https://github.com/striller/BloomTracker#readme
Project-URL: Changelog, https://github.com/striller/BloomTracker/blob/main/CHANGELOG.md
Classifier: Programming Language :: Python :: 3
Classifier: Programming Language :: Python :: 3.7
Classifier: Programming Language :: Python :: 3.8
Classifier: Programming Language :: Python :: 3.9
Classifier: Programming Language :: Python :: 3.10
Classifier: Programming Language :: Python :: 3.11
Classifier: Programming Language :: Python :: 3.12
Classifier: Programming Language :: Python :: 3.13
Classifier: License :: OSI Approved :: GNU General Public License v3 or later (GPLv3+)
Classifier: Operating System :: OS Independent
Classifier: Topic :: Scientific/Engineering :: Atmospheric Science
Classifier: Intended Audience :: Developers
Classifier: Intended Audience :: Science/Research
Classifier: Development Status :: 5 - Production/Stable
Requires-Python: >=3.6
License-File: LICENSE
Requires-Dist: requests>=2.31.0
Requires-Dist: pytz>=2023.3
Requires-Dist: aiohttp>=3.8.0
Requires-Dist: rich>=13.0.0
Requires-Dist: matplotlib>=3.5.0
Requires-Dist: numpy>=1.20.0
Provides-Extra: dev
Requires-Dist: pylint>=3.0.0; extra == "dev"
Requires-Dist: licensecheck>=2025.1.0; extra == "dev"
Requires-Dist: pytest>=7.0.0; extra == "dev"
Dynamic: author
Dynamic: home-page
Dynamic: license-file
Dynamic: requires-python
